BSD
LGPL
LICENSE
MANIFEST.in
README.rst
setup.py
janomecabdic/__init__.py
janomecabdic/dic.h
janomecabdic/dic.pyx
janomecabdic/dic_fallback.py
janomecabdic/mecab_struct.h
janomecabdic.egg-info/PKG-INFO
janomecabdic.egg-info/SOURCES.txt
janomecabdic.egg-info/dependency_links.txt
janomecabdic.egg-info/top_level.txt
janomecabdic/darts/AUTHORS
janomecabdic/darts/BSD
janomecabdic/darts/COPYING
janomecabdic/darts/ChangeLog
janomecabdic/darts/INSTALL
janomecabdic/darts/LGPL
janomecabdic/darts/Makefile.am
janomecabdic/darts/Makefile.in
janomecabdic/darts/NEWS
janomecabdic/darts/README
janomecabdic/darts/acconfig.h
janomecabdic/darts/aclocal.m4
janomecabdic/darts/config.guess
janomecabdic/darts/config.h.in
janomecabdic/darts/config.sub
janomecabdic/darts/configure
janomecabdic/darts/configure.in
janomecabdic/darts/darts.cpp
janomecabdic/darts/darts.h
janomecabdic/darts/darts.h.in
janomecabdic/darts/darts.spec.in
janomecabdic/darts/install-sh
janomecabdic/darts/missing
janomecabdic/darts/mkdarts.cpp
janomecabdic/darts/mkinstalldirs
janomecabdic/darts/stamp-h.in
janomecabdic/darts/doc/darts.css
janomecabdic/darts/doc/index.html
janomecabdic/darts/tests/Makefile.am
janomecabdic/darts/tests/Makefile.in
janomecabdic/darts/tests/linux.words
janomecabdic/darts/tests/mkipa.pl
janomecabdic/darts/tests/test1.sh