Metadata-Version: 1.1
Name: janomecabdic
Version: 0.1.3
Summary: MeCab dictionary access library for janome
Home-page: https://github.com/nakagami/janomecabdic/
Author: Hajime Nakagami
Author-email: nakagami@gmail.com
License: LGPL2,BSD
Keywords: janome,MeCab
Platform: UNKNOWN
Classifier: Development Status :: 4 - Beta
Classifier: Programming Language :: Python
Classifier: Programming Language :: Python :: 3
